bpreveal/.pylintrc
bpreveal/Makefile
bpreveal/__init__.py
bpreveal/bedUtils.py
bpreveal/callbacks.py
bpreveal/checkJson.py
bpreveal/colors.py
bpreveal/gaOptimize.py
bpreveal/generators.py
bpreveal/interpretFlat.py
bpreveal/interpretPisa.py
bpreveal/jaccard.py
bpreveal/layers.py
bpreveal/lengthCalc.py
bpreveal/logUtils.py
bpreveal/losses.py
bpreveal/makeLossPlots.py
bpreveal/makePisaFigure.py
bpreveal/makePredictions.py
bpreveal/makePredictionsBed.py
bpreveal/makePredictionsFasta.py
bpreveal/metrics.py
bpreveal/models.py
bpreveal/motifAddQuantiles.py
bpreveal/motifScan.py
bpreveal/motifSeqletCutoffs.py
bpreveal/motifUtils.py
bpreveal/plotting.py
bpreveal/predictToBigwig.py
bpreveal/prepareBed.py
bpreveal/prepareTrainingData.py
bpreveal/schema.py
bpreveal/shapToBigwig.py
bpreveal/shapToNumpy.py
bpreveal/showModel.py
bpreveal/showTrainingProgress.py
bpreveal/tox.ini
bpreveal/trainCombinedModel.py
bpreveal/trainSoloModel.py
bpreveal/trainTransformationModel.py
bpreveal/training.py
bpreveal/ushuffle.py
bpreveal/utils.py
bpreveal/internal/constants.py
bpreveal/internal/crashQueue.py
bpreveal/internal/disableTensorflowLogging.py
bpreveal/internal/files.py
bpreveal/internal/interpretUtils.py
bpreveal/internal/interpreter.py
bpreveal/internal/libjaccard.c
bpreveal/internal/libjaccard.cpython-312-x86_64-linux-gnu.so
bpreveal/internal/libjaccard.pyf
bpreveal/internal/libslide.c
bpreveal/internal/libslide.cpython-312-x86_64-linux-gnu.so
bpreveal/internal/libslide.pyf
bpreveal/internal/libushuffle.c
bpreveal/internal/libushuffle.cpython-312-x86_64-linux-gnu.so
bpreveal/internal/libushuffle.pyf
bpreveal/internal/plotUtils.py
bpreveal/internal/predictUtils.py
bpreveal/internal/shap.py
bpreveal/schematools/addNoise.schema
bpreveal/schematools/base.schema
bpreveal/schematools/build.py
bpreveal/schematools/interpretFlat.schema
bpreveal/schematools/interpretPisa.schema
bpreveal/schematools/makePisaFigure.schema
bpreveal-5.2.2.dist-info/METADATA
bpreveal-5.2.2.dist-info/WHEEL
bpreveal-5.2.2.dist-info/entry_points.txt
bpreveal-5.2.2.dist-info/RECORD
bpreveal-5.2.2.dist-info/licenses/COPYING
