Metadata-Version: 2.4
Name: bpreveal
Version: 5.2.2
Summary: BPReveal is a suite of tools for deep learning on genomics data.
Author-Email: "Charles McAnany, Ph.D." <bpreveal@charlesmcanany.com>
License-Expression: GPL-2.0-or-later
License-File: COPYING
Classifier: Development Status :: 5 - Production/Stable
Classifier: Intended Audience :: Science/Research
Classifier: Programming Language :: Python :: 3.12
Classifier: Programming Language :: C
Classifier: Topic :: Scientific/Engineering :: Bio-Informatics
Classifier: Topic :: Scientific/Engineering :: Artificial Intelligence
Classifier: Operating System :: POSIX :: Linux
Project-URL: Homepage, https://github.com/mmtrebuchet/bpreveal
Requires-Python: <3.13,>=3.12
Requires-Dist: h5py>=3.13.0
Requires-Dist: jsonschema>=4.23.0
Requires-Dist: matplotlib>=3.10.1
Requires-Dist: meson>=1.7.2
Requires-Dist: modisco>=2.4.0
Requires-Dist: numpy>=2.0
Requires-Dist: pybedtools>=0.12.0
Requires-Dist: pybigwig>=0.3.24
Requires-Dist: pysam>=0.23.0
Requires-Dist: tensorflow-probability>=0.25.0
Requires-Dist: tensorflow[and-cuda]>=2.20.0
Requires-Dist: tf-keras>=2.20.0
Requires-Dist: tqdm>=4.67.1
